MANIFEST.in
README.txt
VERSION.txt
setup.py
rosapi/__init__.py
rosapi/cli-example.py
rosapi/retryloop.py
rosapi/socket_utils.py
rosapi.egg-info/PKG-INFO
rosapi.egg-info/SOURCES.txt
rosapi.egg-info/dependency_links.txt
rosapi.egg-info/top_level.txt
rosapi.egg-info/zip-safe