Metadata-Version: 1.1
Name: rosapi
Version: 0.1.14
Summary: Routerboard API
Home-page: https://github.com/jellonek/rosapi
Author: Piotr Skamruk
Author-email: piotr.skamruk@gmail.com
License: UNKNOWN
Keywords: mikrotik routerboard ros api
Platform: UNKNOWN
Classifier: Development Status :: 2 - Pre-Alpha
Classifier: Topic :: Software Development :: Libraries
Classifier: Topic :: System :: Systems Administration
